env_spec.py
env_spec-0.2.0.dist-info/METADATA
env_spec-0.2.0.dist-info/RECORD
env_spec-0.2.0.dist-info/WHEEL
env_spec-0.2.0.dist-info/top_level.txt
